semantics/__init__.py
semantics/data_control/__init__.py
semantics/data_control/base.py
semantics/data_control/controllers.py
semantics/data_control/transactions.py
semantics/data_structs/__init__.py
semantics/data_structs/controller_data.py
semantics/data_structs/element_data.py
semantics/data_structs/interface.py
semantics/data_structs/operation_contexts.py
semantics/data_structs/transaction_data.py
semantics/data_types/__init__.py
semantics/data_types/allocators.py
semantics/data_types/comparable.py
semantics/data_types/data_access.py
semantics/data_types/exceptions.py
semantics/data_types/indices.py
semantics/data_types/language_ids.py
semantics/data_types/set_unions.py
semantics/data_types/typedefs.py
semantics/graph_layer/__init__.py
semantics/graph_layer/connections.py
semantics/graph_layer/elements.py
semantics/graph_layer/graph_db.py
semantics/graph_layer/interface.py
semantics/kb_layer/__init__.py
semantics/kb_layer/builtin_labels.py
semantics/kb_layer/builtin_patterns.py
semantics/kb_layer/builtin_roles.py
semantics/kb_layer/connections.py
semantics/kb_layer/evidence.py
semantics/kb_layer/hook_registry.py
semantics/kb_layer/interface.py
semantics/kb_layer/knowledge_base.py
semantics/kb_layer/schema.py
semantics/kb_layer/schema_attributes.py
semantics/kb_layer/schema_registry.py
semantics/kb_layer/trigger_queues.py
semantics/kb_layer/orm/__init__.py
semantics/kb_layer/orm/_divisibility_schema.py
semantics/kb_layer/orm/_hook_schema.py
semantics/kb_layer/orm/_instance_schema.py
semantics/kb_layer/orm/_kind_schema.py
semantics/kb_layer/orm/_pattern_match_schema.py
semantics/kb_layer/orm/_pattern_schema.py
semantics/kb_layer/orm/_time_schema.py
semantics/kb_layer/orm/_trigger_schema.py
semantics/kb_layer/orm/_word_schema.py
semantics_nlu-0.0.dist-info/LICENSE
semantics_nlu-0.0.dist-info/METADATA
semantics_nlu-0.0.dist-info/WHEEL
semantics_nlu-0.0.dist-info/top_level.txt
semantics_nlu-0.0.dist-info/RECORD
