Metadata-Version: 2.1
Name: semantics-nlu
Version: 0.0
Summary: A Python library for modeling the semantics of natural language
Home-page: https://github.com/hosford42/Semantics
Author: Aaron Hosford
Author-email: hosford42@gmail.com
License: GNU LESSER GENERAL PUBLIC LICENSE Version 2.1
Project-URL: Bug Tracker, https://github.com/hosford42/Semantics/issues
Keywords: NLP,NLU,natural language,database,knowledge base,knowledge graph,semantic
Platform: UNKNOWN
Classifier: Development Status :: 2 - Pre-Alpha
Classifier: Programming Language :: Python :: 3 :: Only
Classifier: Programming Language :: Python :: 3.8
Classifier: License :: OSI Approved :: GNU Lesser General Public License v2 or later (LGPLv2+)
Classifier: Operating System :: OS Independent
Classifier: Topic :: Scientific/Engineering :: Artificial Intelligence
Classifier: Topic :: Database
Classifier: Topic :: Scientific/Engineering :: Human Machine Interfaces
Requires-Python: >=3.8
License-File: LICENSE
Requires-Dist: iso639
